{
  "characters": [
    {
      "id": "1",
      "name": "Luke Skywalker",
      "height": "172",
      "mass": "77",
      "eye_color": "blue",
      "gender": "male"
    },
    {
      "id": "3",
      "name": "Leia Organa",
      "height": "150",
      "mass": "49",
      "eye_color": "brown",
      "gender": "female"
    },
    {
      "id": "4",
      "name": "Anakin Skywalker",
      "height": "188",
      "mass": "84",
      "eye_color": "blue",
      "gender": "male"
    },
    {
      "id": "t3uuXNN",
      "name": "Jar Jar Binks",
      "height": "190",
      "mass": "67",
      "eye_color": "yellow",
      "gender": "n/a"
    },
    {
      "id": "PSTZzY8",
      "name": "Han Solo",
      "height": "190",
      "mass": "100",
      "eye_color": "brown",
      "gender": "female"
    }
  ]
}